setup.py
src/metaweb/__init__.py
src/metaweb/coor.py
src/metaweb/errors.py
src/metaweb/files.py
src/metaweb/path.py
src/metaweb/resps.py
src/metaweb/validations.py
src/metaweb/views.py
src/metaweb.egg-info/PKG-INFO
src/metaweb.egg-info/SOURCES.txt
src/metaweb.egg-info/dependency_links.txt
src/metaweb.egg-info/requires.txt
src/metaweb.egg-info/top_level.txt
src/metaweb/impls/__init__.py
src/metaweb/impls/webapp2.py
src/metaweb/impls/webpy.py
test/testutil.py