Metadata-Version: 1.1
Name: metaweb
Version: 1.7.6
Summary: A web framework based on other web frameworks.
Home-page: https://package-insights.appspot.com/packages/metaweb
Author: Mengchen LEE
Author-email: CooledCoffee@gmail.com
License: UNKNOWN
Platform: UNKNOWN
Classifier: Development Status :: 4 - Beta
Classifier: Intended Audience :: Developers
Classifier: Operating System :: OS Independent
Classifier: Programming Language :: Python
Classifier: Programming Language :: Python :: 2
Classifier: Topic :: Software Development :: Libraries
